astronomy_types.py
astronomy_types-1.0.2.dist-info/LICENSE
astronomy_types-1.0.2.dist-info/METADATA
astronomy_types-1.0.2.dist-info/WHEEL
astronomy_types-1.0.2.dist-info/top_level.txt
astronomy_types-1.0.2.dist-info/RECORD
