Metadata-Version: 2.1
Name: astronomy_types
Version: 1.0.2
Summary: Type hints for Python astronomy projects
Home-page: https://github.com/Arturius771/astronomy_types
Author: Artur Foden
Author-email: 
Classifier: Programming Language :: Python :: 3
Requires-Python: >=3.12.4
License-File: LICENSE
